{"items": [{"kind": "youtube#channel", "statistics": {"commentCount": "9", "viewCount": "9931093", "videoCount": "4685", "subscriberCount": "5781", "hiddenSubscriberCount": false}, "contentDetails": {"relatedPlaylists": {"likes": "LLPzHPq56sXSjl1nGeYYLLXA", "favorites": "FLPzHPq56sXSjl1nGeYYLLXA", "uploads": "UUPzHPq56sXSjl1nGeYYLLXA"}, "googlePlusUserId": "110096333342763180632"}, "brandingSettings": {"image": {"bannerImageUrl": "http://s.ytimg.com/yts/img/channels/c4/default_banner-vfl7DRgTn.png"}, "channel": {"description": "CBS \uad50\uacc4 \ub274\uc2a4\uc758 \uc720\ud29c\ube0c \uacf5\uc2dd \ucc44\ub110\uc785\ub2c8\ub2e4. \ub77c\ub514\uc624 \ub274\uc2a4\ub294 (\uc218\ub3c4\uad8c) FM 98.1\uc5d0\uc11c \uc544\uce68 6\uc2dc 5\ubd84, \uc624\uc804 11\uc2dc 50\ubd84, \ubc24 8\uc2dc\uc5d0 \ud558\uace0\uc694, CBS TV \ub274\uc2a4\ub294 \ubcf8\ubc29\uc740 \ubc24 9\uc2dc 40\ubd84\uc5d0, \uc7ac\ubc29\uc740 \uc544\uce68 8\uc2dc\uc640 \ub0ae 1\uc2dc\uc5d0 \ubc29\uc601\ud569\ub2c8\ub2e4.", "title": "TheCBSCROSS", "showBrowseView": true, "featuredChannelsTitle": "\ucd94\ucc9c \ucc44\ub110", "featuredChannelsUrls": ["UCa97kDUvLn9OSn9xTX0uM_g", "UCgheNMc3gGHLsT-RISdCzDQ", "UCOxTKOnVCi-D409o7ainG-g", "UCYS8BlH8-6_MIrkCQJIblbw"], "profileColor": "#1F0300", "keywords": "CBS \uad50\uacc4\ub274\uc2a4 CBSTV", "showRelatedChannels": true}, "hints": [{"property": "channel.modules.show_comments.bool", "value": "True"}, {"property": "channel.featured_tab.template.string", "value": "Everything"}]}, "snippet": {"thumbnails": {"default": {"url": "https://yt3.ggpht.com/-ZVOXyvGe2qw/AAAAAAAAAAI/AAAAAAAAAAA/TY7mNQL9cSg/s88-c-k-no-rj-c0xffffff/photo.jpg"}, "high": {"url": "https://yt3.ggpht.com/-ZVOXyvGe2qw/AAAAAAAAAAI/AAAAAAAAAAA/TY7mNQL9cSg/s240-c-k-no-rj-c0xffffff/photo.jpg"}, "medium": {"url": "https://yt3.ggpht.com/-ZVOXyvGe2qw/AAAAAAAAAAI/AAAAAAAAAAA/TY7mNQL9cSg/s240-c-k-no-rj-c0xffffff/photo.jpg"}}, "localized": {"description": "CBS \uad50\uacc4 \ub274\uc2a4\uc758 \uc720\ud29c\ube0c \uacf5\uc2dd \ucc44\ub110\uc785\ub2c8\ub2e4. \ub77c\ub514\uc624 \ub274\uc2a4\ub294 (\uc218\ub3c4\uad8c) FM 98.1\uc5d0\uc11c \uc544\uce68 6\uc2dc 5\ubd84, \uc624\uc804 11\uc2dc 50\ubd84, \ubc24 8\uc2dc\uc5d0 \ud558\uace0\uc694, CBS TV \ub274\uc2a4\ub294 \ubcf8\ubc29\uc740 \ubc24 9\uc2dc 40\ubd84\uc5d0, \uc7ac\ubc29\uc740 \uc544\uce68 8\uc2dc\uc640 \ub0ae 1\uc2dc\uc5d0 \ubc29\uc601\ud569\ub2c8\ub2e4.", "title": "TheCBSCROSS"}, "description": "CBS \uad50\uacc4 \ub274\uc2a4\uc758 \uc720\ud29c\ube0c \uacf5\uc2dd \ucc44\ub110\uc785\ub2c8\ub2e4. \ub77c\ub514\uc624 \ub274\uc2a4\ub294 (\uc218\ub3c4\uad8c) FM 98.1\uc5d0\uc11c \uc544\uce68 6\uc2dc 5\ubd84, \uc624\uc804 11\uc2dc 50\ubd84, \ubc24 8\uc2dc\uc5d0 \ud558\uace0\uc694, CBS TV \ub274\uc2a4\ub294 \ubcf8\ubc29\uc740 \ubc24 9\uc2dc 40\ubd84\uc5d0, \uc7ac\ubc29\uc740 \uc544\uce68 8\uc2dc\uc640 \ub0ae 1\uc2dc\uc5d0 \ubc29\uc601\ud569\ub2c8\ub2e4.", "publishedAt": "2011-07-12T05:11:18.000Z", "title": "TheCBSCROSS"}, "etag": "\"kiOs9cZLH2FUp6r6KJ8eyq_LIOk/xc2Vy755pki-klDpm1JXEouXAzA\"", "id": "UCPzHPq56sXSjl1nGeYYLLXA"}], "kind": "youtube#channelListResponse", "etag": "\"kiOs9cZLH2FUp6r6KJ8eyq_LIOk/29unl31FT3pMLvmiJ5bTG4w_0FM\"", "pageInfo": {"resultsPerPage": 1, "totalResults": 1}}