{"items": [{"status": {"publicStatsViewable": true, "privacyStatus": "public", "uploadStatus": "processed", "license": "youtube", "embeddable": true}, "topicDetails": {"topicIds": ["/m/030b_2", "/m/0bclbf", "/m/01j25p", "/m/0bs_x"], "relevantTopicIds": ["/m/0r4kr10", "/m/0k4j", "/m/0k4j", "/m/07yv9"]}, "kind": "youtube#video", "statistics": {"commentCount": "1028", "viewCount": "614712", "favoriteCount": "0", "dislikeCount": "796", "likeCount": "1058"}, "contentDetails": {"duration": "PT2M57S", "definition": "hd", "licensedContent": true, "dimension": "2d", "caption": "false"}, "snippet": {"thumbnails": {"default": {"url": "https://i.ytimg.com/vi/3ggaYYYf2SM/default.jpg", "width": 120, "height": 90}, "high": {"url": "https://i.ytimg.com/vi/3ggaYYYf2SM/hqdefault.jpg", "width": 480, "height": 360}, "medium": {"url": "https://i.ytimg.com/vi/3ggaYYYf2SM/mqdefault.jpg", "width": 320, "height": 180}, "maxres": {"url": "https://i.ytimg.com/vi/3ggaYYYf2SM/maxresdefault.jpg", "width": 1280, "height": 720}, "standard": {"url": "https://i.ytimg.com/vi/3ggaYYYf2SM/sddefault.jpg", "width": 640, "height": 480}}, "title": "SRT CHALLENGER 392 VS. CAMARO ZL1....SURPRISING! #MOPARORNOCAR", "localized": {"description": "While returning from Myrtle Beach the #SRTLIFE crew ran into a very COCKY ZL1 owner...so we had to give him a piece of HUMBLE PIE!!! LOL!!!\n\nWant to see your SRT ride on www.srtlife.com?? Submit your pics and videos to submissions@srtlife.com", "title": "SRT CHALLENGER 392 VS. CAMARO ZL1....SURPRISING! #MOPARORNOCAR"}, "channelId": "UCYiBTlpEXb4J97XpACjlosw", "publishedAt": "2014-05-27T21:42:47.000Z", "liveBroadcastContent": "none", "channelTitle": "SRT LIFE", "categoryId": "24", "tags": ["Dodge Challenger (Automobile Model)", "challenger", "srt", "Street & Racing Technology (Business Operation)", "camaro", "ZL1", "supercharger", "supercharged", "race", "drag", "torque", "horsepower", "dodge", "mopar", "Drag Racing (Sport)", "Chevrolet Camaro (Automobile Generation)", "Chevrolet Camaro (Automobile Model)", "chevrolet", "chrysler", "borla", "myrtle beach", "black bike week", "2014"], "description": "While returning from Myrtle Beach the #SRTLIFE crew ran into a very COCKY ZL1 owner...so we had to give him a piece of HUMBLE PIE!!! LOL!!!\n\nWant to see your SRT ride on www.srtlife.com?? Submit your pics and videos to submissions@srtlife.com   "}, "player": {"embedHtml": "<iframe width=\"640\" height=\"360\" src=\"//www.youtube.com/embed/3ggaYYYf2SM\" frameborder=\"0\" allowfullscreen></iframe>"}, "etag": "\"abQHWywil_AkNqdqji7_FqiK-u4/KY9Id04PWqzC0lm0I6HaAWZTGu8\"", "id": "3ggaYYYf2SM"}], "kind": "youtube#videoListResponse", "etag": "\"abQHWywil_AkNqdqji7_FqiK-u4/VBQRYesTMpIU0wDRIUbc4CMdt6g\"", "pageInfo": {"resultsPerPage": 1, "totalResults": 1}}