{"items": [{"status": {"publicStatsViewable": true, "privacyStatus": "public", "uploadStatus": "processed", "license": "youtube", "embeddable": true}, "topicDetails": {"topicIds": ["/m/0kscy0"], "relevantTopicIds": ["/m/05jhg", "/m/0d8926", "/m/03jl0_", "/m/02pnshq", "/m/0f96bl", "/m/05jhg"]}, "kind": "youtube#video", "statistics": {"commentCount": "148", "viewCount": "20939", "favoriteCount": "0", "dislikeCount": "87", "likeCount": "51"}, "contentDetails": {"definition": "sd", "projection": "rectangular", "caption": "false", "duration": "PT4M3S", "licensedContent": true, "dimension": "2d"}, "snippet": {"thumbnails": {"default": {"url": "https://i.ytimg.com/vi/3hZSlIHu6EQ/default.jpg", "width": 120, "height": 90}, "high": {"url": "https://i.ytimg.com/vi/3hZSlIHu6EQ/hqdefault.jpg", "width": 480, "height": 360}, "medium": {"url": "https://i.ytimg.com/vi/3hZSlIHu6EQ/mqdefault.jpg", "width": 320, "height": 180}, "standard": {"url": "https://i.ytimg.com/vi/3hZSlIHu6EQ/sddefault.jpg", "width": 640, "height": 480}}, "title": "Bandila: Duterte urged to waive bank secrecy over allegations of hidden wealth", "localized": {"description": "Itinanggi ni Mayor Rodrigo Duterte ang alegasyon ni Sen. Antonio Trillanes na mayroon siyang tagong yaman. Hinamon din siya ng mga kalaban sa pagkapangulo na ilabas ang bank accounts para patunayan ito.\n\nSubscribe to the ABS-CBN News channel! - http://bit.ly/TheABSCBNNews\n\nWatch the full episodes of Bandila on TFC.TV  \nhttp://bit.ly/BANDILA-TFCTV\nand on IWANT.TV for Philippine viewers, click:\nhttp://bit.ly/BANDILA-IWANTV\n\nVisit our website at http://news.abs-cbn.com\nFacebook: https://www.facebook.com/abscbnNEWS\nTwitter: https://twitter.com/abscbnnews", "title": "Bandila: Duterte urged to waive bank secrecy over allegations of hidden wealth"}, "channelId": "UCE2606prvXQc_noEqKxVJXA", "publishedAt": "2016-04-28T00:59:15.000Z", "liveBroadcastContent": "none", "channelTitle": "ABS-CBN News", "categoryId": "25", "tags": ["ABS-CBN", "ABS-CBN News", "ABS-CBN Philippines", "Philippine News", "News", "Philippines", "latest videos", "Bandila", "Zen Hernandez", "Rodrigo Duterte", "halalan2016", "hidden wealth", "bpi", "bank account", "Antonio Trillanes", "April 28 2016", "20160428news"], "description": "Itinanggi ni Mayor Rodrigo Duterte ang alegasyon ni Sen. Antonio Trillanes na mayroon siyang tagong yaman. Hinamon din siya ng mga kalaban sa pagkapangulo na ilabas ang bank accounts para patunayan ito.\n\nSubscribe to the ABS-CBN News channel! - http://bit.ly/TheABSCBNNews\n\nWatch the full episodes of Bandila on TFC.TV  \nhttp://bit.ly/BANDILA-TFCTV\nand on IWANT.TV for Philippine viewers, click:\nhttp://bit.ly/BANDILA-IWANTV\n\nVisit our website at http://news.abs-cbn.com\nFacebook: https://www.facebook.com/abscbnNEWS\nTwitter: https://twitter.com/abscbnnews"}, "player": {"embedHtml": "<iframe width=\"480\" height=\"360\" src=\"//www.youtube.com/embed/3hZSlIHu6EQ\" frameborder=\"0\" allowfullscreen></iframe>"}, "etag": "\"kiOs9cZLH2FUp6r6KJ8eyq_LIOk/Bx15d-SsTVL1JRU5qRGykEHDzwo\"", "id": "3hZSlIHu6EQ"}], "kind": "youtube#videoListResponse", "etag": "\"kiOs9cZLH2FUp6r6KJ8eyq_LIOk/IBkyKLlrDGJcdJ5y0hDhP31p2_8\"", "pageInfo": {"resultsPerPage": 1, "totalResults": 1}}