{"items": [{"status": {"publicStatsViewable": true, "privacyStatus": "public", "uploadStatus": "processed", "license": "youtube", "embeddable": true}, "topicDetails": {"topicIds": ["/m/0ds72z0", "/m/01mw1"], "relevantTopicIds": ["/m/025vk0g", "/m/0ds72z0", "/m/0bzvm2", "/m/025zzc", "/m/0k80c", "/m/03hf_rm", "/m/01mw1"]}, "kind": "youtube#video", "statistics": {"commentCount": "2841", "viewCount": "238952", "favoriteCount": "0", "dislikeCount": "1512", "likeCount": "4383"}, "contentDetails": {"duration": "PT5M25S", "definition": "hd", "licensedContent": true, "dimension": "2d", "caption": "false"}, "snippet": {"thumbnails": {"default": {"url": "https://i.ytimg.com/vi/0Si_xuUrKZM/default.jpg", "width": 120, "height": 90}, "high": {"url": "https://i.ytimg.com/vi/0Si_xuUrKZM/hqdefault.jpg", "width": 480, "height": 360}, "medium": {"url": "https://i.ytimg.com/vi/0Si_xuUrKZM/mqdefault.jpg", "width": 320, "height": 180}, "maxres": {"url": "https://i.ytimg.com/vi/0Si_xuUrKZM/maxresdefault.jpg", "width": 1280, "height": 720}, "standard": {"url": "https://i.ytimg.com/vi/0Si_xuUrKZM/sddefault.jpg", "width": 640, "height": 480}}, "title": "TFTW: Top Ten MOBAs", "localized": {"description": "https://www.youtube.com/watch?v=4g5UvHzZiVY\nClick here to watch TFTW: Top Ten Physics Games!\n\nSteve and Larson take their beef to the arena of battle as they countdown the top ten MOBAs. \n\n- - - - - - - - - - - - -\n\nSign up to receive updates, offers, and information from Machinima.\nhttp://bit.ly/MachinimaNewsletter\n\nFOR MORE INSIDE GAMING, GO TO:\nhttp://www.youtube.com/user/InSideGaming\n\nWANT TO JOIN THE MACHINIMA AFFILIATE PROGRAM? FILL OUT AN APPLICATION HERE:\nLink: http://bit.ly/13ACBHg", "title": "TFTW: Top Ten MOBAs"}, "channelId": "UCcMTZY1rFXO3Rj44D5VMyiw", "publishedAt": "2014-02-20T14:00:07.000Z", "liveBroadcastContent": "none", "channelTitle": "Machinima", "categoryId": "43", "tags": ["moba", "pc", "xbox", "playstation", "video game", "multiplayer online battle arena", "league of legends", "LoL", "DOTA 2", "Defense of the Ancients", "AirMech", "Smite", "Bloodline Champions", "Heroes of Order and Chaos", "Awesomenauts", "SmashMuck Champions", "Demigod", "Arena of Heroes", "countdown", "top", "ten", "list", "TFTW", "Ten For The Win"], "description": "https://www.youtube.com/watch?v=4g5UvHzZiVY\nClick here to watch TFTW: Top Ten Physics Games!\n\nSteve and Larson take their beef to the arena of battle as they countdown the top ten MOBAs. \n\n- - - - - - - - - - - - -\n\nSign up to receive updates, offers, and information from Machinima.\nhttp://bit.ly/MachinimaNewsletter\n\nFOR MORE INSIDE GAMING, GO TO:\nhttp://www.youtube.com/user/InSideGaming\n\nWANT TO JOIN THE MACHINIMA AFFILIATE PROGRAM? FILL OUT AN APPLICATION HERE:\nLink: http://bit.ly/13ACBHg"}, "player": {"embedHtml": "<iframe width=\"640\" height=\"360\" src=\"//www.youtube.com/embed/0Si_xuUrKZM\" frameborder=\"0\" allowfullscreen></iframe>"}, "etag": "\"abQHWywil_AkNqdqji7_FqiK-u4/osr09YzHxNrgv0i13jVNbYtxmgM\"", "id": "0Si_xuUrKZM"}], "kind": "youtube#videoListResponse", "etag": "\"abQHWywil_AkNqdqji7_FqiK-u4/FnkESLAlhB45ay1PquyriuGYu2Y\"", "pageInfo": {"resultsPerPage": 1, "totalResults": 1}}