{"items": [{"status": {"publicStatsViewable": true, "privacyStatus": "public", "uploadStatus": "processed", "license": "youtube", "embeddable": true}, "topicDetails": {"topicIds": ["/m/07j6ty", "/m/0cqt90"], "relevantTopicIds": ["/m/05qt0", "/m/09x0r", "/m/0434q7", "/m/0qfhx0f", "/m/0d3k14", "/m/04gwy", "/m/05qt0", "/m/098wr"]}, "kind": "youtube#video", "statistics": {"commentCount": "1489", "viewCount": "234738", "favoriteCount": "0", "dislikeCount": "885", "likeCount": "2874"}, "contentDetails": {"definition": "hd", "projection": "rectangular", "caption": "true", "duration": "PT12M21S", "licensedContent": true, "dimension": "2d"}, "snippet": {"thumbnails": {"default": {"url": "https://i.ytimg.com/vi/gqljp91yejM/default.jpg", "width": 120, "height": 90}, "high": {"url": "https://i.ytimg.com/vi/gqljp91yejM/hqdefault.jpg", "width": 480, "height": 360}, "medium": {"url": "https://i.ytimg.com/vi/gqljp91yejM/mqdefault.jpg", "width": 320, "height": 180}, "maxres": {"url": "https://i.ytimg.com/vi/gqljp91yejM/maxresdefault.jpg", "width": 1280, "height": 720}, "standard": {"url": "https://i.ytimg.com/vi/gqljp91yejM/sddefault.jpg", "width": 640, "height": 480}}, "title": "Trump: Ted Cruz\u2019s Dad Helped Kill Kennedy", "defaultAudioLanguage": "en", "localized": {"description": "Donald Trump is upset that Rafael Cruz is telling people to vote for his son, Ted Cruz, over Trump. Trump cited a National Enquirer article, that alleges Rafael Cruz had met with Lee Harvey Oswald just before the Kennedy assassination. John Iadarola and Jimmy Dore, hosts of The Young Turks, break it down. Tell us what you think in the comment section below.\n\n\u201cDonald Trump on Tuesday alleged that Ted Cruz\u2019s father was with John F. Kennedy\u2019s assassin shortly before he murdered the president, parroting a National Enquirer story claiming that Rafael Cruz was pictured with Lee Harvey Oswald handing out pro-Fidel Castro pamphlets in New Orleans in 1963.\n\nA Cruz campaign spokesperson told the Miami Herald, which pointed out numerous flaws in the Enquirer story, that it was \u201canother garbage story in a tabloid full of garbage.\u201d\n\n\u201cHis father was with Lee Harvey Oswald prior to Oswald's being \u2014 you know, shot. I mean, the whole thing is ridiculous,\u201d Trump said Tuesday during a phone interview with Fox News. \u201cWhat is this, right prior to his being shot, and nobody even brings it up. They don't even talk about that. That was reported, and nobody talks about it.\u201d\n\nRead more here: http://www.politico.com/blogs/2016-gop-primary-live-updates-and-results/2016/05/trump-ted-cruz-father-222730\n\nHosts: John Iadarola, Jimmy Dore\n\nCast: John Iadarola, Jimmy Dore\n\n***\n\nThe Largest Online News Show in the World. Hosted by Cenk Uygur and Ana Kasparian. LIVE STREAMING weekdays 6-8pm ET. http://www.tytnetwork.com/live\n\nYoung Turk (n), 1. Young progressive or insurgent member of an institution, movement, or political party. 2. Young person who rebels against authority or societal expectations. (American Heritage Dictionary)\n\nDownload audio and video of the full two hour show on-demand + the members-only post game show by becoming a member at http://www.tytnetwork.com/join/. Your membership supports the day to day operations and is vital for our continued success and growth.\n\nGet The Young Turks Mobile App Today!\n\nDownload the iOS version here: https://itunes.apple.com/us/app/the-young-turks/id412793195?ls=1&mt=8\n\nDownload the Android version here: https://play.google.com/store/apps/details?id=com.tyt", "title": "Trump: Ted Cruz\u2019s Dad Helped Kill Kennedy"}, "channelId": "UC1yBKRuGpC1tSM73A0ZjYjQ", "publishedAt": "2016-05-04T00:00:19.000Z", "liveBroadcastContent": "none", "channelTitle": "The Young Turks", "categoryId": "25", "tags": ["John Iadarola", "Jimmy Dore", "TYT", "The Young Turks", "progressive", "liberal", "news", "politics", "rafael cruz", "father", "ted cruz", "christian", "evangelical", "presidential candidate", "160503__TA03EnquiringMinds"], "description": "Donald Trump is upset that Rafael Cruz is telling people to vote for his son, Ted Cruz, over Trump. Trump cited a National Enquirer article, that alleges Rafael Cruz had met with Lee Harvey Oswald just before the Kennedy assassination. John Iadarola and Jimmy Dore, hosts of The Young Turks, break it down. Tell us what you think in the comment section below.\n\n\u201cDonald Trump on Tuesday alleged that Ted Cruz\u2019s father was with John F. Kennedy\u2019s assassin shortly before he murdered the president, parroting a National Enquirer story claiming that Rafael Cruz was pictured with Lee Harvey Oswald handing out pro-Fidel Castro pamphlets in New Orleans in 1963.\n\nA Cruz campaign spokesperson told the Miami Herald, which pointed out numerous flaws in the Enquirer story, that it was \u201canother garbage story in a tabloid full of garbage.\u201d\n\n\u201cHis father was with Lee Harvey Oswald prior to Oswald's being \u2014 you know, shot. I mean, the whole thing is ridiculous,\u201d Trump said Tuesday during a phone interview with Fox News. \u201cWhat is this, right prior to his being shot, and nobody even brings it up. They don't even talk about that. That was reported, and nobody talks about it.\u201d\n\nRead more here: http://www.politico.com/blogs/2016-gop-primary-live-updates-and-results/2016/05/trump-ted-cruz-father-222730\n\nHosts: John Iadarola, Jimmy Dore\n\nCast: John Iadarola, Jimmy Dore\n\n***\n\nThe Largest Online News Show in the World. Hosted by Cenk Uygur and Ana Kasparian. LIVE STREAMING weekdays 6-8pm ET. http://www.tytnetwork.com/live\n\nYoung Turk (n), 1. Young progressive or insurgent member of an institution, movement, or political party. 2. Young person who rebels against authority or societal expectations. (American Heritage Dictionary)\n\nDownload audio and video of the full two hour show on-demand + the members-only post game show by becoming a member at http://www.tytnetwork.com/join/. Your membership supports the day to day operations and is vital for our continued success and growth.\n\nGet The Young Turks Mobile App Today!\n\nDownload the iOS version here: https://itunes.apple.com/us/app/the-young-turks/id412793195?ls=1&mt=8\n\nDownload the Android version here: https://play.google.com/store/apps/details?id=com.tyt"}, "player": {"embedHtml": "<iframe width=\"640\" height=\"360\" src=\"//www.youtube.com/embed/gqljp91yejM\" frameborder=\"0\" allowfullscreen></iframe>"}, "etag": "\"kiOs9cZLH2FUp6r6KJ8eyq_LIOk/GGa15-Af6W10rfPMaakkYtLt9-A\"", "id": "gqljp91yejM"}], "kind": "youtube#videoListResponse", "etag": "\"kiOs9cZLH2FUp6r6KJ8eyq_LIOk/UxSM2YwrVw_d8LWNIofLZgf6rUM\"", "pageInfo": {"resultsPerPage": 1, "totalResults": 1}}