{"items": [{"status": {"publicStatsViewable": true, "privacyStatus": "public", "uploadStatus": "processed", "license": "youtube", "embeddable": true}, "topicDetails": {"topicIds": ["/m/05ngt2", "/m/02vxy_", "/m/02d_t6", "/m/06wzv"], "relevantTopicIds": ["/m/05xjb", "/m/027cqyf", "/m/01l_mq", "/m/06x2m", "/m/09w32k", "/m/098wr", "/m/06bvp"]}, "kind": "youtube#video", "statistics": {"commentCount": "12171", "viewCount": "643856", "favoriteCount": "0", "dislikeCount": "1050", "likeCount": "2934"}, "contentDetails": {"duration": "PT10M31S", "definition": "sd", "licensedContent": true, "dimension": "2d", "caption": "false"}, "snippet": {"thumbnails": {"default": {"url": "https://i.ytimg.com/vi/i7GLGfHZdos/default.jpg", "width": 120, "height": 90}, "high": {"url": "https://i.ytimg.com/vi/i7GLGfHZdos/hqdefault.jpg", "width": 480, "height": 360}, "medium": {"url": "https://i.ytimg.com/vi/i7GLGfHZdos/mqdefault.jpg", "width": 320, "height": 180}}, "title": "Catholic Exorcist Warns: Pope Francis is NOT the Legitimate Pope & Satan Has Taken Over the Throne", "localized": {"description": "Father Jack Ashcraft, Catholic Priest and Exorcist, warns that Pope Francis is NOT the legitimate Pope and Satan has pulled off a coup!\nYour local priest may NOT be legitimate either. Souls in Danger!\n\nhttp://www.trueexorcist.com/", "title": "Catholic Exorcist Warns: Pope Francis is NOT the Legitimate Pope & Satan Has Taken Over the Throne"}, "channelId": "UCA5hOHgxCuXdQsg99Yd7HFw", "publishedAt": "2014-06-25T18:46:48.000Z", "liveBroadcastContent": "none", "channelTitle": "Josh Tolley", "categoryId": "25", "tags": ["Pope", "Exorcism", "Exorcist", "Ouji Board", "Possession", "Possessed", "Pope Francis", "Catholicism", "Vatican", "Vatican Secrets", "Satan", "Satanic", "Occult", "Witchcraft", "Wicca", "NWO", "New World Order", "Priest", "Steve Quayle", "Tom Horn", "Prophecy", "Bible", "Torah", "Torah Portion", "Alex Jones", "Infowars", "Red Pill", "Porc Fest", "PorcFest", "Shabbat", "Michael Rood", "Jim Staley", "Apostasy", "119 Ministries", "Sex", "Illuminati", "Rome", "God", "YHVH", "YHWH", "Cult", "Jack Van Impe", "Glenn Beck", "Coast to Coast AM", "George Knapp", "Iggy Azalea (Celebrity)"], "description": "Father Jack Ashcraft, Catholic Priest and Exorcist, warns that Pope Francis is NOT the legitimate Pope and Satan has pulled off a coup!\nYour local priest may NOT be legitimate either. Souls in Danger!\n\nhttp://www.trueexorcist.com/"}, "player": {"embedHtml": "<iframe width=\"480\" height=\"360\" src=\"//www.youtube.com/embed/i7GLGfHZdos\" frameborder=\"0\" allowfullscreen></iframe>"}, "etag": "\"abQHWywil_AkNqdqji7_FqiK-u4/nJA2ZF5ny0FadeMvHPPgdcpDhmk\"", "id": "i7GLGfHZdos"}], "kind": "youtube#videoListResponse", "etag": "\"abQHWywil_AkNqdqji7_FqiK-u4/ZfOxnRl62B5nwZOtzF5oPY_kAHU\"", "pageInfo": {"resultsPerPage": 1, "totalResults": 1}}